masksdk/__init__.py
masksdk/call_infer_and_mask.py
masksdk/mask.py
masksdk/sdk.py
masksdk-1.1.1.dist-info/LICENSE
masksdk-1.1.1.dist-info/METADATA
masksdk-1.1.1.dist-info/WHEEL
masksdk-1.1.1.dist-info/top_level.txt
masksdk-1.1.1.dist-info/RECORD
