Metadata-Version: 2.1
Name: masksdk
Version: 1.1.1
Summary: sdk for mask
License: UNKNOWN
Platform: UNKNOWN
Classifier: Programming Language :: Python :: 3
Classifier: License :: OSI Approved :: GNU General Public License v3 (GPLv3)
Classifier: Operating System :: OS Independent
Requires-Python: >=3.6
License-File: LICENSE
Requires-Dist: Pillow
Requires-Dist: requests
Provides-Extra: tests
Requires-Dist: numpy ; extra == 'tests'
Requires-Dist: opencv-python ; extra == 'tests'
Requires-Dist: Pillow ; extra == 'tests'
Requires-Dist: requests ; extra == 'tests'
Requires-Dist: setuptools ; extra == 'tests'
